training_loop/__init__.py
training_loop/callbacks/__init__.py
training_loop/callbacks/callback.py
training_loop/callbacks/early_stopping.py
training_loop/callbacks/model_checkpoint.py
training_loop/callbacks/tensorboard_logger.py
training_loop/distributed.py
training_loop/exceptions.py
training_loop/progress_reporter.py
training_loop/training_loops/__init__.py
training_loop/training_loops/distributed_training_loop.py
training_loop/training_loops/distributed_training_step.py
training_loop/training_loops/simple_training_step.py
training_loop/training_loops/training_loop.py
training_loop/training_loops/training_step.py
training_loop/training_loops/utils.py
training_loop/types.py
torch_training_loop-0.1.3.dist-info/LICENSE
torch_training_loop-0.1.3.dist-info/METADATA
torch_training_loop-0.1.3.dist-info/WHEEL
torch_training_loop-0.1.3.dist-info/RECORD
