Metadata-Version: 2.1
Name: torch-training-loop
Version: 0.1.3
Summary: Simple Keras-inspired Training Loop for Pytorch.
Home-page: https://github.com/beekill95/torch-training-loop
License: MIT
Author: beekill
Author-email: nguyenmbquan95@gmail.com
Requires-Python: >=3.8,<4.0
Classifier: License :: OSI Approved :: MIT License
Classifier: Programming Language :: Python :: 3
Classifier: Programming Language :: Python :: 3.8
Classifier: Programming Language :: Python :: 3.9
Classifier: Programming Language :: Python :: 3.10
Classifier: Programming Language :: Python :: 3.11
Classifier: Topic :: Scientific/Engineering
Classifier: Topic :: Scientific/Engineering :: Artificial Intelligence
Classifier: Topic :: Software Development
Classifier: Topic :: Software Development :: Libraries
Classifier: Topic :: Software Development :: Libraries :: Python Modules
Requires-Dist: numpy
Requires-Dist: pandas
Requires-Dist: torch
Requires-Dist: torcheval
Requires-Dist: tqdm
Project-URL: CHANGELOG, https://github.com/beekill95/torch-training-loop/blob/main/CHANGELOG.md
Project-URL: Repository, https://github.com/beekill95/torch-training-loop
